eurogui/__init__.py
eurogui-0.0.dist-info/METADATA
eurogui-0.0.dist-info/WHEEL
eurogui-0.0.dist-info/RECORD
