Metadata-Version: 2.3
Name: eurogui
Version: 0.0
Summary: A modern, hardware-accelerated C++ GUI framework (Python bindings coming soon).
Author: Kalom
Requires-Python: >=3.10,<4.0
Classifier: Programming Language :: Python :: 3
Classifier: Programming Language :: Python :: 3.10
Classifier: Programming Language :: Python :: 3.11
Classifier: Programming Language :: Python :: 3.12
Classifier: Programming Language :: Python :: 3.13
